LICENSE.txt
MANIFEST.in
README.md
setup.cfg
setup.py
ojitos369_oracle_db/__init__.py
ojitos369_oracle_db/oracle_db.py
ojitos369_oracle_db.egg-info/PKG-INFO
ojitos369_oracle_db.egg-info/SOURCES.txt
ojitos369_oracle_db.egg-info/dependency_links.txt
ojitos369_oracle_db.egg-info/requires.txt
ojitos369_oracle_db.egg-info/top_level.txt