Metadata-Version: 2.1
Name: ojitos369_oracle_db
Version: 2.1.4
Summary: Funciones con conexiones a bases de datos
Home-page: https://github.com/Ojitos369/ojitos369-pip
Author: Ojitos369
Author-email: ojitos369@gmail.com
License: LGPL v3
Keywords: Utilidades de ojitos369
Classifier: Programming Language :: Python
Classifier: Programming Language :: Python :: 3.8
Classifier: Programming Language :: Python :: 3.9
Classifier: Programming Language :: Python :: 3.10
Classifier: Programming Language :: Python :: 3.11
Classifier: Programming Language :: Python :: 3.12
License-File: LICENSE.txt
Requires-Dist: cx_Oracle
Requires-Dist: ojitos369
Requires-Dist: pandas
